trainwave_jupyter/__init__.py
trainwave_jupyter/_version.py
trainwave_jupyter/handlers.py
trainwave_jupyter/io.py
trainwave_jupyter/labextension/package.json
trainwave_jupyter/labextension/schemas/trainwave-jupyter/auth.json
trainwave_jupyter/labextension/schemas/trainwave-jupyter/package.json.orig
trainwave_jupyter/labextension/schemas/trainwave-jupyter/plugin.json
trainwave_jupyter/labextension/static/576.049da8808272770a13bf.js
trainwave_jupyter/labextension/static/728.fcb35a3c4bc6962e3ac2.js
trainwave_jupyter/labextension/static/remoteEntry.b3f485999018a1b68312.js
trainwave_jupyter/labextension/static/style.js
trainwave_jupyter/labextension/static/third-party-licenses.json
trainwave_jupyter/tests/__init__.py
trainwave_jupyter/tests/test_handlers.py
trainwave_jupyter/tests/test_init.py
trainwave_jupyter/tests/test_integration.py
trainwave_jupyter/tests/test_io.py
trainwave_jupyter-0.1.2.data/data/etc/jupyter/jupyter_server_config.d/trainwave-jupyter.json
trainwave_jupyter-0.1.2.data/data/etc/jupyter/jupyter_server_config.d/trainwave.json
trainwave_jupyter-0.1.2.data/data/share/jupyter/labextensions/trainwave-jupyter/package.json
trainwave_jupyter-0.1.2.data/data/share/jupyter/labextensions/trainwave-jupyter/schemas/trainwave-jupyter/auth.json
trainwave_jupyter-0.1.2.data/data/share/jupyter/labextensions/trainwave-jupyter/schemas/trainwave-jupyter/package.json.orig
trainwave_jupyter-0.1.2.data/data/share/jupyter/labextensions/trainwave-jupyter/schemas/trainwave-jupyter/plugin.json
trainwave_jupyter-0.1.2.data/data/share/jupyter/labextensions/trainwave-jupyter/static/576.049da8808272770a13bf.js
trainwave_jupyter-0.1.2.data/data/share/jupyter/labextensions/trainwave-jupyter/static/728.fcb35a3c4bc6962e3ac2.js
trainwave_jupyter-0.1.2.data/data/share/jupyter/labextensions/trainwave-jupyter/static/remoteEntry.b3f485999018a1b68312.js
trainwave_jupyter-0.1.2.data/data/share/jupyter/labextensions/trainwave-jupyter/static/style.js
trainwave_jupyter-0.1.2.dist-info/METADATA
trainwave_jupyter-0.1.2.dist-info/WHEEL
trainwave_jupyter-0.1.2.dist-info/licenses/LICENSE
trainwave_jupyter-0.1.2.dist-info/RECORD
