Metadata-Version: 2.4
Name: trainwave-jupyter
Version: 0.1.2
Summary: Make trainwave.ai available right in your notebook for fast, cheap and efficient GPU workloads.
Project-URL: Homepage, https://gitlab.com/ezml1/jupyter-extension
Project-URL: Bug Tracker, https://gitlab.com/ezml1/jupyter-extension/issues
Project-URL: Repository, https://gitlab.com/ezml1/jupyter-extension.git
Author-email: "Trainwave.ai" <johan@trainwave.ai>
License: BSD 3-Clause License
License-File: LICENSE
Keywords: jupyter,jupyterlab,jupyterlab-extension
Classifier: Framework :: Jupyter
Classifier: Framework :: Jupyter :: JupyterLab
Classifier: Framework :: Jupyter :: JupyterLab :: 4
Classifier: Framework :: Jupyter :: JupyterLab :: Extensions
Classifier: Framework :: Jupyter :: JupyterLab :: Extensions :: Prebuilt
Classifier: License :: OSI Approved :: BSD License
Classifier: Programming Language :: Python
Classifier: Programming Language :: Python :: 3
Classifier: Programming Language :: Python :: 3.9
Classifier: Programming Language :: Python :: 3.10
Classifier: Programming Language :: Python :: 3.11
Classifier: Programming Language :: Python :: 3.12
Classifier: Programming Language :: Python :: 3.13
Requires-Python: >=3.9
Requires-Dist: aiofiles>=24.1.0
Requires-Dist: aiohttp>=3.8.0
Requires-Dist: jupyter-server<3,>=2.4.0
Requires-Dist: jupyterlab>=4.4.7
Requires-Dist: loguru>=0.7.3
Requires-Dist: nbconvert
Requires-Dist: nbformat
Requires-Dist: pathspec>=0.12.1
Requires-Dist: tqdm>=4.67.1
Provides-Extra: test
Requires-Dist: coverage; extra == 'test'
Requires-Dist: pytest; extra == 'test'
Requires-Dist: pytest-asyncio; extra == 'test'
Requires-Dist: pytest-cov; extra == 'test'
Requires-Dist: pytest-jupyter[server]>=0.6.0; extra == 'test'
